[
    {
        "dia": 15,
        "hora": 16,
        "minuto": 29,
        "codigo_agrupacion": 169,
        "votos_agrupacion": 3748,
        "porc_final_agrupacion": 6462,
        "cargos_electos": 0
    },
    {
        "dia": 15,
        "hora": 16,
        "minuto": 29,
        "codigo_agrupacion": 529,
        "votos_agrupacion": 851,
        "porc_final_agrupacion": 1467,
        "cargos_electos": 0
    },
    {
        "dia": 15,
        "hora": 16,
        "minuto": 29,
        "codigo_agrupacion": 165,
        "votos_agrupacion": 439,
        "porc_final_agrupacion": 757,
        "cargos_electos": 0
    },
    {
        "dia": 15,
        "hora": 16,
        "minuto": 29,
        "codigo_agrupacion": 3,
        "votos_agrupacion": 386,
        "porc_final_agrupacion": 666,
        "cargos_electos": 0
    },
    {
        "dia": 15,
        "hora": 16,
        "minuto": 29,
        "codigo_agrupacion": 501,
        "votos_agrupacion": 264,
        "porc_final_agrupacion": 455,
        "cargos_electos": 0
    },
    {
        "dia": 15,
        "hora": 16,
        "minuto": 29,
        "codigo_agrupacion": 522,
        "votos_agrupacion": 112,
        "porc_final_agrupacion": 193,
        "cargos_electos": 0
    }
]