[
    {
        "dia": 15,
        "hora": 16,
        "minuto": 29,
        "codigo_agrupacion": 138,
        "votos_agrupacion": 981,
        "porc_final_agrupacion": 4308,
        "cargos_electos": 0
    },
    {
        "dia": 15,
        "hora": 16,
        "minuto": 29,
        "codigo_agrupacion": 137,
        "votos_agrupacion": 587,
        "porc_final_agrupacion": 2578,
        "cargos_electos": 0
    },
    {
        "dia": 15,
        "hora": 16,
        "minuto": 29,
        "codigo_agrupacion": 135,
        "votos_agrupacion": 336,
        "porc_final_agrupacion": 1476,
        "cargos_electos": 0
    },
    {
        "dia": 15,
        "hora": 16,
        "minuto": 29,
        "codigo_agrupacion": 131,
        "votos_agrupacion": 200,
        "porc_final_agrupacion": 878,
        "cargos_electos": 0
    },
    {
        "dia": 15,
        "hora": 16,
        "minuto": 29,
        "codigo_agrupacion": 132,
        "votos_agrupacion": 132,
        "porc_final_agrupacion": 580,
        "cargos_electos": 0
    },
    {
        "dia": 15,
        "hora": 16,
        "minuto": 29,
        "codigo_agrupacion": 133,
        "votos_agrupacion": 41,
        "porc_final_agrupacion": 180,
        "cargos_electos": 0
    }
]