{
    "mesas_totales": 11,
    "mesas_escrutadas": 5,
    "porc_mesas_escrutadas": 4545,
    "electores": 3210,
    "votantes": 1145,
    "participacion_sobre_censo": 3567,
    "participacion_sobre_escrutado": 7752,
    "electores_escrutados": 1477,
    "porc_electores_escrutados": 4601,
    "votos_validos": 1145,
    "porc_votos_validos": 3567,
    "votos_positivos": 961,
    "porc_votos_positivos": 8393,
    "votos_en_blanco": 101,
    "porc_votos_en_blanco": 882,
    "votos_nulos": 8,
    "porc_votos_nulos": 70,
    "votos_recurridos_impugnados": 75,
    "porc_votos_recurridos_impugnados": 655,
    "cargos_a_elegir": 0,
    "dia": 15,
    "hora": 16,
    "minuto": 29
}