{
    "mesas_totales": 22,
    "mesas_escrutadas": 7,
    "porc_mesas_escrutadas": 3182,
    "electores": 7548,
    "votantes": 1954,
    "participacion_sobre_censo": 2589,
    "participacion_sobre_escrutado": 8038,
    "electores_escrutados": 2431,
    "porc_electores_escrutados": 3221,
    "votos_validos": 1954,
    "porc_votos_validos": 2589,
    "votos_positivos": 1638,
    "porc_votos_positivos": 8383,
    "votos_en_blanco": 174,
    "porc_votos_en_blanco": 890,
    "votos_nulos": 16,
    "porc_votos_nulos": 82,
    "votos_recurridos_impugnados": 126,
    "porc_votos_recurridos_impugnados": 645,
    "cargos_a_elegir": 0,
    "dia": 15,
    "hora": 16,
    "minuto": 29
}