{
    "mesas_totales": 32,
    "mesas_escrutadas": 7,
    "porc_mesas_escrutadas": 2188,
    "electores": 10032,
    "votantes": 1926,
    "participacion_sobre_censo": 1920,
    "participacion_sobre_escrutado": 7874,
    "electores_escrutados": 2446,
    "porc_electores_escrutados": 2438,
    "votos_validos": 1926,
    "porc_votos_validos": 1920,
    "votos_positivos": 1329,
    "porc_votos_positivos": 6900,
    "votos_en_blanco": 227,
    "porc_votos_en_blanco": 1179,
    "votos_nulos": 130,
    "porc_votos_nulos": 675,
    "votos_recurridos_impugnados": 240,
    "porc_votos_recurridos_impugnados": 1246,
    "cargos_a_elegir": 0,
    "dia": 15,
    "hora": 16,
    "minuto": 29
}