{
    "mesas_totales": 8,
    "mesas_escrutadas": 6,
    "porc_mesas_escrutadas": 7500,
    "electores": 2451,
    "votantes": 1354,
    "participacion_sobre_censo": 5524,
    "participacion_sobre_escrutado": 7689,
    "electores_escrutados": 1761,
    "porc_electores_escrutados": 7185,
    "votos_validos": 1354,
    "porc_votos_validos": 5524,
    "votos_positivos": 663,
    "porc_votos_positivos": 4897,
    "votos_en_blanco": 214,
    "porc_votos_en_blanco": 1581,
    "votos_nulos": 200,
    "porc_votos_nulos": 1477,
    "votos_recurridos_impugnados": 277,
    "porc_votos_recurridos_impugnados": 2045,
    "cargos_a_elegir": 0,
    "dia": 15,
    "hora": 16,
    "minuto": 29
}