[
    {
        "dia": 15,
        "hora": 16,
        "minuto": 29,
        "codigo_agrupacion": 502,
        "votos_agrupacion": 5496,
        "porc_final_agrupacion": 6881,
        "cargos_electos": 0
    },
    {
        "dia": 15,
        "hora": 16,
        "minuto": 29,
        "codigo_agrupacion": 23,
        "votos_agrupacion": 1248,
        "porc_final_agrupacion": 1562,
        "cargos_electos": 0
    },
    {
        "dia": 15,
        "hora": 16,
        "minuto": 29,
        "codigo_agrupacion": 50,
        "votos_agrupacion": 726,
        "porc_final_agrupacion": 909,
        "cargos_electos": 0
    },
    {
        "dia": 15,
        "hora": 16,
        "minuto": 29,
        "codigo_agrupacion": 501,
        "votos_agrupacion": 518,
        "porc_final_agrupacion": 648,
        "cargos_electos": 0
    }
]