{
    "mesas_totales": 277,
    "mesas_escrutadas": 76,
    "porc_mesas_escrutadas": 2744,
    "electores": 91996,
    "votantes": 19430,
    "participacion_sobre_censo": 2112,
    "participacion_sobre_escrutado": 7887,
    "electores_escrutados": 24635,
    "porc_electores_escrutados": 2678,
    "votos_validos": 19430,
    "porc_votos_validos": 2112,
    "votos_positivos": 16318,
    "porc_votos_positivos": 8398,
    "votos_en_blanco": 1715,
    "porc_votos_en_blanco": 883,
    "votos_nulos": 152,
    "porc_votos_nulos": 78,
    "votos_recurridos_impugnados": 1245,
    "porc_votos_recurridos_impugnados": 641,
    "cargos_a_elegir": 0,
    "dia": 15,
    "hora": 16,
    "minuto": 29
}