{
    "mesas_totales": 22,
    "mesas_escrutadas": 7,
    "porc_mesas_escrutadas": 3182,
    "electores": 6412,
    "votantes": 1776,
    "participacion_sobre_censo": 2770,
    "participacion_sobre_escrutado": 7914,
    "electores_escrutados": 2244,
    "porc_electores_escrutados": 3500,
    "votos_validos": 1776,
    "porc_votos_validos": 2770,
    "votos_positivos": 1495,
    "porc_votos_positivos": 8418,
    "votos_en_blanco": 155,
    "porc_votos_en_blanco": 873,
    "votos_nulos": 13,
    "porc_votos_nulos": 73,
    "votos_recurridos_impugnados": 113,
    "porc_votos_recurridos_impugnados": 636,
    "cargos_a_elegir": 0,
    "dia": 15,
    "hora": 16,
    "minuto": 29
}