{
    "mesas_totales": 43,
    "mesas_escrutadas": 9,
    "porc_mesas_escrutadas": 2093,
    "electores": 13519,
    "votantes": 2061,
    "participacion_sobre_censo": 1525,
    "participacion_sobre_escrutado": 7982,
    "electores_escrutados": 2582,
    "porc_electores_escrutados": 1910,
    "votos_validos": 2061,
    "porc_votos_validos": 1525,
    "votos_positivos": 1735,
    "porc_votos_positivos": 8418,
    "votos_en_blanco": 181,
    "porc_votos_en_blanco": 878,
    "votos_nulos": 15,
    "porc_votos_nulos": 73,
    "votos_recurridos_impugnados": 130,
    "porc_votos_recurridos_impugnados": 631,
    "cargos_a_elegir": 0,
    "dia": 15,
    "hora": 16,
    "minuto": 29
}