[
    {
        "dia": 15,
        "hora": 16,
        "minuto": 29,
        "codigo_agrupacion": 526,
        "votos_agrupacion": 599,
        "porc_final_agrupacion": 5598,
        "cargos_electos": 0
    },
    {
        "dia": 15,
        "hora": 16,
        "minuto": 29,
        "codigo_agrupacion": 501,
        "votos_agrupacion": 164,
        "porc_final_agrupacion": 1533,
        "cargos_electos": 0
    },
    {
        "dia": 15,
        "hora": 16,
        "minuto": 29,
        "codigo_agrupacion": 518,
        "votos_agrupacion": 128,
        "porc_final_agrupacion": 1196,
        "cargos_electos": 0
    },
    {
        "dia": 15,
        "hora": 16,
        "minuto": 29,
        "codigo_agrupacion": 153,
        "votos_agrupacion": 108,
        "porc_final_agrupacion": 1009,
        "cargos_electos": 0
    },
    {
        "dia": 15,
        "hora": 16,
        "minuto": 29,
        "codigo_agrupacion": 821,
        "votos_agrupacion": 71,
        "porc_final_agrupacion": 664,
        "cargos_electos": 0
    }
]