{
    "mesas_totales": 502,
    "mesas_escrutadas": 135,
    "porc_mesas_escrutadas": 2689,
    "electores": 174030,
    "votantes": 37160,
    "participacion_sobre_censo": 2135,
    "participacion_sobre_escrutado": 7942,
    "electores_escrutados": 46788,
    "porc_electores_escrutados": 2689,
    "votos_validos": 37160,
    "porc_votos_validos": 2135,
    "votos_positivos": 27453,
    "porc_votos_positivos": 7388,
    "votos_en_blanco": 4022,
    "porc_votos_en_blanco": 1082,
    "votos_nulos": 1794,
    "porc_votos_nulos": 483,
    "votos_recurridos_impugnados": 3891,
    "porc_votos_recurridos_impugnados": 1047,
    "cargos_a_elegir": 0,
    "dia": 15,
    "hora": 16,
    "minuto": 29
}