{
    "mesas_totales": 175,
    "mesas_escrutadas": 43,
    "porc_mesas_escrutadas": 2457,
    "electores": 58291,
    "votantes": 11257,
    "participacion_sobre_censo": 1931,
    "participacion_sobre_escrutado": 7881,
    "electores_escrutados": 14284,
    "porc_electores_escrutados": 2450,
    "votos_validos": 11257,
    "porc_votos_validos": 1931,
    "votos_positivos": 5499,
    "porc_votos_positivos": 4885,
    "votos_en_blanco": 1782,
    "porc_votos_en_blanco": 1583,
    "votos_nulos": 1667,
    "porc_votos_nulos": 1481,
    "votos_recurridos_impugnados": 2309,
    "porc_votos_recurridos_impugnados": 2051,
    "cargos_a_elegir": 0,
    "dia": 15,
    "hora": 16,
    "minuto": 29
}