[
    {
        "dia": 15,
        "hora": 16,
        "minuto": 29,
        "codigo_agrupacion": 138,
        "votos_agrupacion": 16691,
        "porc_final_agrupacion": 6040,
        "cargos_electos": 0
    },
    {
        "dia": 15,
        "hora": 16,
        "minuto": 29,
        "codigo_agrupacion": 131,
        "votos_agrupacion": 4356,
        "porc_final_agrupacion": 1576,
        "cargos_electos": 0
    },
    {
        "dia": 15,
        "hora": 16,
        "minuto": 29,
        "codigo_agrupacion": 132,
        "votos_agrupacion": 2746,
        "porc_final_agrupacion": 994,
        "cargos_electos": 0
    },
    {
        "dia": 15,
        "hora": 16,
        "minuto": 29,
        "codigo_agrupacion": 137,
        "votos_agrupacion": 2145,
        "porc_final_agrupacion": 776,
        "cargos_electos": 0
    },
    {
        "dia": 15,
        "hora": 16,
        "minuto": 29,
        "codigo_agrupacion": 145,
        "votos_agrupacion": 1697,
        "porc_final_agrupacion": 614,
        "cargos_electos": 0
    }
]