{
    "mesas_totales": 170,
    "mesas_escrutadas": 46,
    "porc_mesas_escrutadas": 2706,
    "electores": 57200,
    "votantes": 12209,
    "participacion_sobre_censo": 2134,
    "participacion_sobre_escrutado": 8012,
    "electores_escrutados": 15239,
    "porc_electores_escrutados": 2664,
    "votos_validos": 12209,
    "porc_votos_validos": 2134,
    "votos_positivos": 5380,
    "porc_votos_positivos": 4407,
    "votos_en_blanco": 2051,
    "porc_votos_en_blanco": 1680,
    "votos_nulos": 2051,
    "porc_votos_nulos": 1680,
    "votos_recurridos_impugnados": 2727,
    "porc_votos_recurridos_impugnados": 2233,
    "cargos_a_elegir": 0,
    "dia": 15,
    "hora": 16,
    "minuto": 29
}