{
    "mesas_totales": 9,
    "mesas_escrutadas": 4,
    "porc_mesas_escrutadas": 4444,
    "electores": 2457,
    "votantes": 1070,
    "participacion_sobre_censo": 4355,
    "participacion_sobre_escrutado": 7648,
    "electores_escrutados": 1399,
    "porc_electores_escrutados": 5694,
    "votos_validos": 1070,
    "porc_votos_validos": 4355,
    "votos_positivos": 735,
    "porc_votos_positivos": 6869,
    "votos_en_blanco": 127,
    "porc_votos_en_blanco": 1187,
    "votos_nulos": 73,
    "porc_votos_nulos": 682,
    "votos_recurridos_impugnados": 135,
    "porc_votos_recurridos_impugnados": 1262,
    "cargos_a_elegir": 0,
    "dia": 15,
    "hora": 16,
    "minuto": 29
}