[
    {
        "dia": 15,
        "hora": 16,
        "minuto": 29,
        "codigo_agrupacion": 138,
        "votos_agrupacion": 1831,
        "porc_final_agrupacion": 6092,
        "cargos_electos": 0
    },
    {
        "dia": 15,
        "hora": 16,
        "minuto": 29,
        "codigo_agrupacion": 131,
        "votos_agrupacion": 508,
        "porc_final_agrupacion": 1691,
        "cargos_electos": 0
    },
    {
        "dia": 15,
        "hora": 16,
        "minuto": 29,
        "codigo_agrupacion": 133,
        "votos_agrupacion": 270,
        "porc_final_agrupacion": 899,
        "cargos_electos": 0
    },
    {
        "dia": 15,
        "hora": 16,
        "minuto": 29,
        "codigo_agrupacion": 137,
        "votos_agrupacion": 213,
        "porc_final_agrupacion": 709,
        "cargos_electos": 0
    },
    {
        "dia": 15,
        "hora": 16,
        "minuto": 29,
        "codigo_agrupacion": 135,
        "votos_agrupacion": 183,
        "porc_final_agrupacion": 609,
        "cargos_electos": 0
    }
]