{
    "mesas_totales": 4,
    "mesas_escrutadas": 1,
    "porc_mesas_escrutadas": 2500,
    "electores": 1199,
    "votantes": 162,
    "participacion_sobre_censo": 1351,
    "participacion_sobre_escrutado": 5110,
    "electores_escrutados": 317,
    "porc_electores_escrutados": 2644,
    "votos_validos": 162,
    "porc_votos_validos": 1351,
    "votos_positivos": 93,
    "porc_votos_positivos": 5741,
    "votos_en_blanco": 22,
    "porc_votos_en_blanco": 1358,
    "votos_nulos": 17,
    "porc_votos_nulos": 1049,
    "votos_recurridos_impugnados": 30,
    "porc_votos_recurridos_impugnados": 1852,
    "cargos_a_elegir": 0,
    "dia": 15,
    "hora": 16,
    "minuto": 29
}