[
    {
        "dia": 15,
        "hora": 16,
        "minuto": 29,
        "codigo_agrupacion": 522,
        "votos_agrupacion": 20475,
        "porc_final_agrupacion": 4828,
        "cargos_electos": 0
    },
    {
        "dia": 15,
        "hora": 16,
        "minuto": 29,
        "codigo_agrupacion": 3,
        "votos_agrupacion": 6626,
        "porc_final_agrupacion": 1563,
        "cargos_electos": 0
    },
    {
        "dia": 15,
        "hora": 16,
        "minuto": 29,
        "codigo_agrupacion": 501,
        "votos_agrupacion": 5006,
        "porc_final_agrupacion": 1181,
        "cargos_electos": 0
    },
    {
        "dia": 15,
        "hora": 16,
        "minuto": 29,
        "codigo_agrupacion": 165,
        "votos_agrupacion": 4319,
        "porc_final_agrupacion": 1019,
        "cargos_electos": 0
    },
    {
        "dia": 15,
        "hora": 16,
        "minuto": 29,
        "codigo_agrupacion": 529,
        "votos_agrupacion": 3312,
        "porc_final_agrupacion": 781,
        "cargos_electos": 0
    },
    {
        "dia": 15,
        "hora": 16,
        "minuto": 29,
        "codigo_agrupacion": 169,
        "votos_agrupacion": 2662,
        "porc_final_agrupacion": 628,
        "cargos_electos": 0
    }
]