{
    "mesas_totales": 621,
    "mesas_escrutadas": 166,
    "porc_mesas_escrutadas": 2673,
    "electores": 215667,
    "votantes": 45810,
    "participacion_sobre_censo": 2124,
    "participacion_sobre_escrutado": 7939,
    "electores_escrutados": 57704,
    "porc_electores_escrutados": 2676,
    "votos_validos": 45810,
    "porc_votos_validos": 2124,
    "votos_positivos": 38459,
    "porc_votos_positivos": 8395,
    "votos_en_blanco": 4050,
    "porc_votos_en_blanco": 884,
    "votos_nulos": 361,
    "porc_votos_nulos": 79,
    "votos_recurridos_impugnados": 2940,
    "porc_votos_recurridos_impugnados": 642,
    "cargos_a_elegir": 0,
    "dia": 15,
    "hora": 16,
    "minuto": 29
}