{
    "mesas_totales": 53,
    "mesas_escrutadas": 15,
    "porc_mesas_escrutadas": 2830,
    "electores": 16023,
    "votantes": 3532,
    "participacion_sobre_censo": 2204,
    "participacion_sobre_escrutado": 7932,
    "electores_escrutados": 4453,
    "porc_electores_escrutados": 2779,
    "votos_validos": 3532,
    "porc_votos_validos": 2204,
    "votos_positivos": 2617,
    "porc_votos_positivos": 7409,
    "votos_en_blanco": 380,
    "porc_votos_en_blanco": 1076,
    "votos_nulos": 170,
    "porc_votos_nulos": 481,
    "votos_recurridos_impugnados": 365,
    "porc_votos_recurridos_impugnados": 1034,
    "cargos_a_elegir": 0,
    "dia": 15,
    "hora": 16,
    "minuto": 29
}