{
    "mesas_totales": 171,
    "mesas_escrutadas": 47,
    "porc_mesas_escrutadas": 2749,
    "electores": 55939,
    "votantes": 11852,
    "participacion_sobre_censo": 2119,
    "participacion_sobre_escrutado": 7922,
    "electores_escrutados": 14961,
    "porc_electores_escrutados": 2675,
    "votos_validos": 11852,
    "porc_votos_validos": 2119,
    "votos_positivos": 9954,
    "porc_votos_positivos": 8399,
    "votos_en_blanco": 1047,
    "porc_votos_en_blanco": 883,
    "votos_nulos": 92,
    "porc_votos_nulos": 78,
    "votos_recurridos_impugnados": 759,
    "porc_votos_recurridos_impugnados": 640,
    "cargos_a_elegir": 0,
    "dia": 15,
    "hora": 16,
    "minuto": 29
}