{
    "mesas_totales": 103,
    "mesas_escrutadas": 28,
    "porc_mesas_escrutadas": 2718,
    "electores": 33416,
    "votantes": 6776,
    "participacion_sobre_censo": 2028,
    "participacion_sobre_escrutado": 7959,
    "electores_escrutados": 8514,
    "porc_electores_escrutados": 2548,
    "votos_validos": 6776,
    "porc_votos_validos": 2028,
    "votos_positivos": 4345,
    "porc_votos_positivos": 6412,
    "votos_en_blanco": 864,
    "porc_votos_en_blanco": 1275,
    "votos_nulos": 595,
    "porc_votos_nulos": 878,
    "votos_recurridos_impugnados": 972,
    "porc_votos_recurridos_impugnados": 1435,
    "cargos_a_elegir": 0,
    "dia": 15,
    "hora": 16,
    "minuto": 29
}