{
    "mesas_totales": 43,
    "mesas_escrutadas": 6,
    "porc_mesas_escrutadas": 1395,
    "electores": 14585,
    "votantes": 1634,
    "participacion_sobre_censo": 1120,
    "participacion_sobre_escrutado": 8392,
    "electores_escrutados": 1947,
    "porc_electores_escrutados": 1335,
    "votos_validos": 1634,
    "porc_votos_validos": 1120,
    "votos_positivos": 720,
    "porc_votos_positivos": 4406,
    "votos_en_blanco": 275,
    "porc_votos_en_blanco": 1683,
    "votos_nulos": 275,
    "porc_votos_nulos": 1683,
    "votos_recurridos_impugnados": 364,
    "porc_votos_recurridos_impugnados": 2228,
    "cargos_a_elegir": 0,
    "dia": 15,
    "hora": 16,
    "minuto": 24
}