[
    {
        "dia": 15,
        "hora": 16,
        "minuto": 29,
        "codigo_agrupacion": 531,
        "votos_agrupacion": 2753,
        "porc_final_agrupacion": 6864,
        "cargos_electos": 0
    },
    {
        "dia": 15,
        "hora": 16,
        "minuto": 29,
        "codigo_agrupacion": 131,
        "votos_agrupacion": 631,
        "porc_final_agrupacion": 1573,
        "cargos_electos": 0
    },
    {
        "dia": 15,
        "hora": 16,
        "minuto": 29,
        "codigo_agrupacion": 132,
        "votos_agrupacion": 384,
        "porc_final_agrupacion": 957,
        "cargos_electos": 0
    },
    {
        "dia": 15,
        "hora": 16,
        "minuto": 29,
        "codigo_agrupacion": 135,
        "votos_agrupacion": 243,
        "porc_final_agrupacion": 606,
        "cargos_electos": 0
    }
]