{
    "mesas_totales": 266,
    "mesas_escrutadas": 70,
    "porc_mesas_escrutadas": 2632,
    "electores": 91431,
    "votantes": 19406,
    "participacion_sobre_censo": 2122,
    "participacion_sobre_escrutado": 7960,
    "electores_escrutados": 24380,
    "porc_electores_escrutados": 2666,
    "votos_validos": 19406,
    "porc_votos_validos": 2122,
    "votos_positivos": 12411,
    "porc_votos_positivos": 6395,
    "votos_en_blanco": 2485,
    "porc_votos_en_blanco": 1281,
    "votos_nulos": 1714,
    "porc_votos_nulos": 883,
    "votos_recurridos_impugnados": 2796,
    "porc_votos_recurridos_impugnados": 1441,
    "cargos_a_elegir": 0,
    "dia": 15,
    "hora": 16,
    "minuto": 29
}