[
    {
        "dia": 15,
        "hora": 16,
        "minuto": 29,
        "codigo_agrupacion": 138,
        "votos_agrupacion": 1405,
        "porc_final_agrupacion": 4301,
        "cargos_electos": 0
    },
    {
        "dia": 15,
        "hora": 16,
        "minuto": 29,
        "codigo_agrupacion": 137,
        "votos_agrupacion": 843,
        "porc_final_agrupacion": 2581,
        "cargos_electos": 0
    },
    {
        "dia": 15,
        "hora": 16,
        "minuto": 29,
        "codigo_agrupacion": 135,
        "votos_agrupacion": 481,
        "porc_final_agrupacion": 1473,
        "cargos_electos": 0
    },
    {
        "dia": 15,
        "hora": 16,
        "minuto": 29,
        "codigo_agrupacion": 131,
        "votos_agrupacion": 285,
        "porc_final_agrupacion": 873,
        "cargos_electos": 0
    },
    {
        "dia": 15,
        "hora": 16,
        "minuto": 29,
        "codigo_agrupacion": 132,
        "votos_agrupacion": 191,
        "porc_final_agrupacion": 585,
        "cargos_electos": 0
    },
    {
        "dia": 15,
        "hora": 16,
        "minuto": 29,
        "codigo_agrupacion": 133,
        "votos_agrupacion": 61,
        "porc_final_agrupacion": 187,
        "cargos_electos": 0
    }
]