[
    {
        "dia": 15,
        "hora": 16,
        "minuto": 29,
        "codigo_agrupacion": 177,
        "votos_agrupacion": 125700,
        "porc_final_agrupacion": 6784,
        "cargos_electos": 0
    },
    {
        "dia": 15,
        "hora": 16,
        "minuto": 29,
        "codigo_agrupacion": 131,
        "votos_agrupacion": 28939,
        "porc_final_agrupacion": 1562,
        "cargos_electos": 0
    },
    {
        "dia": 15,
        "hora": 16,
        "minuto": 29,
        "codigo_agrupacion": 135,
        "votos_agrupacion": 19017,
        "porc_final_agrupacion": 1026,
        "cargos_electos": 0
    },
    {
        "dia": 15,
        "hora": 16,
        "minuto": 29,
        "codigo_agrupacion": 137,
        "votos_agrupacion": 11629,
        "porc_final_agrupacion": 628,
        "cargos_electos": 0
    }
]