{
    "mesas_totales": 53,
    "mesas_escrutadas": 15,
    "porc_mesas_escrutadas": 2830,
    "electores": 16967,
    "votantes": 3873,
    "participacion_sobre_censo": 2283,
    "participacion_sobre_escrutado": 7893,
    "electores_escrutados": 4907,
    "porc_electores_escrutados": 2892,
    "votos_validos": 3873,
    "porc_votos_validos": 2283,
    "votos_positivos": 1699,
    "porc_votos_positivos": 4387,
    "votos_en_blanco": 653,
    "porc_votos_en_blanco": 1686,
    "votos_nulos": 653,
    "porc_votos_nulos": 1686,
    "votos_recurridos_impugnados": 868,
    "porc_votos_recurridos_impugnados": 2241,
    "cargos_a_elegir": 0,
    "dia": 15,
    "hora": 16,
    "minuto": 29
}