{
    "mesas_totales": 44,
    "mesas_escrutadas": 14,
    "porc_mesas_escrutadas": 3182,
    "electores": 14241,
    "votantes": 3103,
    "participacion_sobre_censo": 2179,
    "participacion_sobre_escrutado": 8051,
    "electores_escrutados": 3854,
    "porc_electores_escrutados": 2706,
    "votos_validos": 3103,
    "porc_votos_validos": 2179,
    "votos_positivos": 1681,
    "porc_votos_positivos": 5417,
    "votos_en_blanco": 459,
    "porc_votos_en_blanco": 1479,
    "votos_nulos": 394,
    "porc_votos_nulos": 1270,
    "votos_recurridos_impugnados": 569,
    "porc_votos_recurridos_impugnados": 1834,
    "cargos_a_elegir": 1,
    "dia": 15,
    "hora": 16,
    "minuto": 29
}