{
    "mesas_totales": 53,
    "mesas_escrutadas": 15,
    "porc_mesas_escrutadas": 2830,
    "electores": 16567,
    "votantes": 3612,
    "participacion_sobre_censo": 2180,
    "participacion_sobre_escrutado": 7902,
    "electores_escrutados": 4571,
    "porc_electores_escrutados": 2759,
    "votos_validos": 3612,
    "porc_votos_validos": 2180,
    "votos_positivos": 2493,
    "porc_votos_positivos": 6902,
    "votos_en_blanco": 425,
    "porc_votos_en_blanco": 1177,
    "votos_nulos": 247,
    "porc_votos_nulos": 684,
    "votos_recurridos_impugnados": 447,
    "porc_votos_recurridos_impugnados": 1237,
    "cargos_a_elegir": 0,
    "dia": 15,
    "hora": 16,
    "minuto": 29
}