[
    {
        "dia": 15,
        "hora": 16,
        "minuto": 29,
        "codigo_agrupacion": 138,
        "votos_agrupacion": 10009,
        "porc_final_agrupacion": 6819,
        "cargos_electos": 0
    },
    {
        "dia": 15,
        "hora": 16,
        "minuto": 29,
        "codigo_agrupacion": 131,
        "votos_agrupacion": 2306,
        "porc_final_agrupacion": 1571,
        "cargos_electos": 0
    },
    {
        "dia": 15,
        "hora": 16,
        "minuto": 29,
        "codigo_agrupacion": 145,
        "votos_agrupacion": 1457,
        "porc_final_agrupacion": 993,
        "cargos_electos": 0
    },
    {
        "dia": 15,
        "hora": 16,
        "minuto": 29,
        "codigo_agrupacion": 137,
        "votos_agrupacion": 906,
        "porc_final_agrupacion": 617,
        "cargos_electos": 0
    }
]