{
    "mesas_totales": 21,
    "mesas_escrutadas": 3,
    "porc_mesas_escrutadas": 1429,
    "electores": 6228,
    "votantes": 601,
    "participacion_sobre_censo": 965,
    "participacion_sobre_escrutado": 8698,
    "electores_escrutados": 691,
    "porc_electores_escrutados": 1110,
    "votos_validos": 601,
    "porc_votos_validos": 965,
    "votos_positivos": 298,
    "porc_votos_positivos": 4958,
    "votos_en_blanco": 95,
    "porc_votos_en_blanco": 1581,
    "votos_nulos": 89,
    "porc_votos_nulos": 1481,
    "votos_recurridos_impugnados": 119,
    "porc_votos_recurridos_impugnados": 1980,
    "cargos_a_elegir": 0,
    "dia": 15,
    "hora": 16,
    "minuto": 9
}